EasyCo/__init__.py
EasyCo/__version__.py
EasyCo/config_file.py
EasyCo/configuration.py
EasyCo/container.py
EasyCo/entry.py
EasyCo/path_container.py
EasyCo/yaml/__init__.py
EasyCo/yaml/yaml.py
EasyCo-0.2.3.dist-info/LICENSE
EasyCo-0.2.3.dist-info/METADATA
EasyCo-0.2.3.dist-info/WHEEL
EasyCo-0.2.3.dist-info/top_level.txt
EasyCo-0.2.3.dist-info/RECORD
