Metadata-Version: 2.1
Name: EasyCo
Version: 0.2.3
Summary: Easy configuration with yaml files
Home-page: https://github.com/spacemanspiff2007/EasyCo
Author: spaceman_spiff
License: UNKNOWN
Project-URL: Documentation, https://easyco.readthedocs.io/
Project-URL: GitHub, https://github.com/spacemanspiff2007/EasyCo
Keywords: yaml,yml,config,configuration,file
Platform: UNKNOWN
Classifier: Development Status :: 4 - Beta
Classifier: License :: OSI Approved :: GNU General Public License v3 or later (GPLv3+)
Classifier: Operating System :: OS Independent
Classifier: Programming Language :: Python :: 3.6
Classifier: Programming Language :: Python :: 3.7
Classifier: Programming Language :: Python :: 3 :: Only
Classifier: Topic :: Software Development :: Libraries
Requires-Dist: ruamel.yaml
Requires-Dist: voluptuous
